MANIFEST.in
setup.py
bbb/__init__.py
bbb/runner.py
bbb/servicebase.py
bbb/services.py
bbb/tcutils.py
bbb/timeutils.py
bbb.egg-info/PKG-INFO
bbb.egg-info/SOURCES.txt
bbb.egg-info/dependency_links.txt
bbb.egg-info/entry_points.txt
bbb.egg-info/not-zip-safe
bbb.egg-info/requires.txt
bbb.egg-info/top_level.txt
bbb/schemas/__init__.py
bbb/schemas/payload.yml