Metadata-Version: 1.0
Name: bbb
Version: 1.5.21
Summary: Buildbot <-> Taskcluster Bridge
Home-page: UNKNOWN
Author: Mozilla Release Engineering
Author-email: UNKNOWN
License: UNKNOWN
Platform: UNKNOWN
